odoo/addons/auth_user_case_insensitive/README.rst
odoo/addons/auth_user_case_insensitive/__init__.py
odoo/addons/auth_user_case_insensitive/__manifest__.py
odoo/addons/auth_user_case_insensitive/hooks.py
odoo/addons/auth_user_case_insensitive/i18n/ar.po
odoo/addons/auth_user_case_insensitive/i18n/auth_user_case_insensitive.pot
odoo/addons/auth_user_case_insensitive/i18n/ca.po
odoo/addons/auth_user_case_insensitive/i18n/da.po
odoo/addons/auth_user_case_insensitive/i18n/de.po
odoo/addons/auth_user_case_insensitive/i18n/el_GR.po
odoo/addons/auth_user_case_insensitive/i18n/es.po
odoo/addons/auth_user_case_insensitive/i18n/es_ES.po
odoo/addons/auth_user_case_insensitive/i18n/fi.po
odoo/addons/auth_user_case_insensitive/i18n/fr.po
odoo/addons/auth_user_case_insensitive/i18n/fr_CH.po
odoo/addons/auth_user_case_insensitive/i18n/fr_FR.po
odoo/addons/auth_user_case_insensitive/i18n/hr.po
odoo/addons/auth_user_case_insensitive/i18n/hr_HR.po
odoo/addons/auth_user_case_insensitive/i18n/it.po
odoo/addons/auth_user_case_insensitive/i18n/nl.po
odoo/addons/auth_user_case_insensitive/i18n/nl_NL.po
odoo/addons/auth_user_case_insensitive/i18n/pt.po
odoo/addons/auth_user_case_insensitive/i18n/pt_BR.po
odoo/addons/auth_user_case_insensitive/i18n/ro.po
odoo/addons/auth_user_case_insensitive/i18n/sl.po
odoo/addons/auth_user_case_insensitive/i18n/tr.po
odoo/addons/auth_user_case_insensitive/i18n/tr_TR.po
odoo/addons/auth_user_case_insensitive/i18n/zh_CN.po
odoo/addons/auth_user_case_insensitive/models/__init__.py
odoo/addons/auth_user_case_insensitive/models/res_users.py
odoo/addons/auth_user_case_insensitive/readme/CONTRIBUTORS.rst
odoo/addons/auth_user_case_insensitive/readme/DESCRIPTION.rst
odoo/addons/auth_user_case_insensitive/readme/INSTALL.rst
odoo/addons/auth_user_case_insensitive/readme/USAGE.rst
odoo/addons/auth_user_case_insensitive/static/description/icon.png
odoo/addons/auth_user_case_insensitive/static/description/index.html
odoo14_addon_auth_user_case_insensitive-14.0.1.0.1.dist-info/METADATA
odoo14_addon_auth_user_case_insensitive-14.0.1.0.1.dist-info/WHEEL
odoo14_addon_auth_user_case_insensitive-14.0.1.0.1.dist-info/top_level.txt
odoo14_addon_auth_user_case_insensitive-14.0.1.0.1.dist-info/RECORD
